[
  {
    "name": "Albania",
    "capital": "Tirana",
    "population": 2800000,
    "independenceOrFormation": "1912",
    "formerColonialPower": "Ottoman Empire",
    "isd_code": "+355",
    "cctld": ".al",
    "countryDescription": "",
    "countryFlag": "🇦🇱",
    "countryImage": null,
    "continent": "Europe"
  },
  {
    "name": "Andorra",
    "capital": "Andorra la Vella",
    "population": 80000,
    "independenceOrFormation": "1278",
    "formerColonialPower": "Not colonized",
    "isd_code": "+376",
    "cctld": ".ad",
    "countryDescription": "",
    "countryFlag": "🇦🇩",
    "countryImage": null,
    "continent": "Europe"
  },
  {
    "name": "Austria",
    "capital": "Vienna",
    "population": 9100000,
    "independenceOrFormation": "1955",
    "formerColonialPower": "Not colonized",
    "isd_code": "+43",
    "cctld": ".at",
    "countryDescription": "",
    "countryFlag": "🇦🇹",
    "countryImage": null,
    "continent": "Europe"
  },
  {
    "name": "Belarus",
    "capital": "Minsk",
    "population": 9200000,
    "independenceOrFormation": "1991",
    "formerColonialPower": "Soviet Union",
    "isd_code": "+375",
    "cctld": ".by",
    "countryDescription": "",
    "countryFlag": "🇧🇾",
    "countryImage": null,
    "continent": "Europe"
  },
  {
    "name": "Belgium",
    "capital": "Brussels",
    "population": 11800000,
    "independenceOrFormation": "1830",
    "formerColonialPower": "Not colonized",
    "isd_code": "+32",
    "cctld": ".be",
    "countryDescription": "",
    "countryFlag": "🇧🇪",
    "countryImage": null,
    "continent": "Europe"
  },
  {
    "name": "Bosnia and Herzegovina",
    "capital": "Sarajevo",
    "population": 3200000,
    "independenceOrFormation": "1992",
    "formerColonialPower": "Yugoslavia",
    "isd_code": "+387",
    "cctld": ".ba",
    "countryDescription": "",
    "countryFlag": "🇧🇦",
    "countryImage": null,
    "continent": "Europe"
  },
  {
    "name": "Bulgaria",
    "capital": "Sofia",
    "population": 6700000,
    "independenceOrFormation": "1908",
    "formerColonialPower": "Ottoman Empire",
    "isd_code": "+359",
    "cctld": ".bg",
    "countryDescription": "",
    "countryFlag": "🇧🇬",
    "countryImage": null,
    "continent": "Europe"
  },
  {
    "name": "Croatia",
    "capital": "Zagreb",
    "population": 3900000,
    "independenceOrFormation": "1991",
    "formerColonialPower": "Yugoslavia",
    "isd_code": "+385",
    "cctld": ".hr",
    "countryDescription": "",
    "countryFlag": "🇭🇷",
    "countryImage": null,
    "continent": "Europe"
  },
  {
    "name": "Czech Republic",
    "capital": "Prague",
    "population": 10700000,
    "independenceOrFormation": "1993",
    "formerColonialPower": "Czechoslovakia",
    "isd_code": "+420",
    "cctld": ".cz",
    "countryDescription": "",
    "countryFlag": "🇨🇿",
    "countryImage": null,
    "continent": "Europe"
  },
  {
    "name": "Denmark",
    "capital": "Copenhagen",
    "population": 6000000,
    "independenceOrFormation": "N/A",
    "formerColonialPower": "Not colonized",
    "isd_code": "+45",
    "cctld": ".dk",
    "countryDescription": "",
    "countryFlag": "🇩🇰",
    "countryImage": null,
    "continent": "Europe"
  },
  {
    "name": "Estonia",
    "capital": "Tallinn",
    "population": 1300000,
    "independenceOrFormation": "1991",
    "formerColonialPower": "Soviet Union",
    "isd_code": "+372",
    "cctld": ".ee",
    "countryDescription": "",
    "countryFlag": "🇪🇪",
    "countryImage": null,
    "continent": "Europe"
  },
  {
    "name": "Finland",
    "capital": "Helsinki",
    "population": 5600000,
    "independenceOrFormation": "1917",
    "formerColonialPower": "Russian Empire",
    "isd_code": "+358",
    "cctld": ".fi",
    "countryDescription": "",
    "countryFlag": "🇫🇮",
    "countryImage": null,
    "continent": "Europe"
  },
  {
    "name": "France",
    "capital": "Paris",
    "population": 68000000,
    "independenceOrFormation": "843",
    "formerColonialPower": "Not colonized",
    "isd_code": "+33",
    "cctld": ".fr",
    "countryDescription": "",
    "countryFlag": "🇫🇷",
    "countryImage": null,
    "continent": "Europe"
  },
  {
    "name": "Germany",
    "capital": "Berlin",
    "population": 84000000,
    "independenceOrFormation": "1871",
    "formerColonialPower": "Not colonized",
    "isd_code": "+49",
    "cctld": ".de",
    "countryDescription": "",
    "countryFlag": "🇩🇪",
    "countryImage": null,
    "continent": "Europe"
  },
  {
    "name": "Greece",
    "capital": "Athens",
    "population": 10400000,
    "independenceOrFormation": "1830",
    "formerColonialPower": "Ottoman Empire",
    "isd_code": "+30",
    "cctld": ".gr",
    "countryDescription": "",
    "countryFlag": "🇬🇷",
    "countryImage": null,
    "continent": "Europe"
  },
  {
    "name": "Hungary",
    "capital": "Budapest",
    "population": 9600000,
    "independenceOrFormation": "1918",
    "formerColonialPower": "Austria-Hungary",
    "isd_code": "+36",
    "cctld": ".hu",
    "countryDescription": "",
    "countryFlag": "🇭🇺",
    "countryImage": null,
    "continent": "Europe"
  },
  {
    "name": "Iceland",
    "capital": "Reykjavík",
    "population": 390000,
    "independenceOrFormation": "1944",
    "formerColonialPower": "Denmark",
    "isd_code": "+354",
    "cctld": ".is",
    "countryDescription": "",
    "countryFlag": "🇮🇸",
    "countryImage": null,
    "continent": "Europe"
  },
  {
    "name": "Ireland",
    "capital": "Dublin",
    "population": 5300000,
    "independenceOrFormation": "1922",
    "formerColonialPower": "United Kingdom",
    "isd_code": "+353",
    "cctld": ".ie",
    "countryDescription": "",
    "countryFlag": "🇮🇪",
    "countryImage": null,
    "continent": "Europe"
  },
  {
    "name": "Italy",
    "capital": "Rome",
    "population": 59000000,
    "independenceOrFormation": "1861",
    "formerColonialPower": "Not colonized",
    "isd_code": "+39",
    "cctld": ".it",
    "countryDescription": "",
    "countryFlag": "🇮🇹",
    "countryImage": null,
    "continent": "Europe"
  },
  {
    "name": "Latvia",
    "capital": "Riga",
    "population": 1900000,
    "independenceOrFormation": "1991",
    "formerColonialPower": "Soviet Union",
    "isd_code": "+371",
    "cctld": ".lv",
    "countryDescription": "",
    "countryFlag": "🇱🇻",
    "countryImage": null,
    "continent": "Europe"
  },
  {
    "name": "Liechtenstein",
    "capital": "Vaduz",
    "population": 39000,
    "independenceOrFormation": "1806",
    "formerColonialPower": "Not colonized",
    "isd_code": "+423",
    "cctld": ".li",
    "countryDescription": "",
    "countryFlag": "🇱🇮",
    "countryImage": null,
    "continent": "Europe"
  },
  {
    "name": "Lithuania",
    "capital": "Vilnius",
    "population": 2800000,
    "independenceOrFormation": "1990",
    "formerColonialPower": "Soviet Union",
    "isd_code": "+370",
    "cctld": ".lt",
    "countryDescription": "",
    "countryFlag": "🇱🇹",
    "countryImage": null,
    "continent": "Europe"
  },
  {
    "name": "Luxembourg",
    "capital": "Luxembourg",
    "population": 670000,
    "independenceOrFormation": "1839",
    "formerColonialPower": "Not colonized",
    "isd_code": "+352",
    "cctld": ".lu",
    "countryDescription": "",
    "countryFlag": "🇱🇺",
    "countryImage": null,
    "continent": "Europe"
  },
  {
    "name": "Malta",
    "capital": "Valletta",
    "population": 560000,
    "independenceOrFormation": "1964",
    "formerColonialPower": "United Kingdom",
    "isd_code": "+356",
    "cctld": ".mt",
    "countryDescription": "",
    "countryFlag": "🇲🇹",
    "countryImage": null,
    "continent": "Europe"
  },
  {
    "name": "Moldova",
    "capital": "Chișinău",
    "population": 2600000,
    "independenceOrFormation": "1991",
    "formerColonialPower": "Soviet Union",
    "isd_code": "+373",
    "cctld": ".md",
    "countryDescription": "",
    "countryFlag": "🇲🇩",
    "countryImage": null,
    "continent": "Europe"
  },
  {
    "name": "Monaco",
    "capital": "Monaco",
    "population": 39000,
    "independenceOrFormation": "1297",
    "formerColonialPower": "Not colonized",
    "isd_code": "+377",
    "cctld": ".mc",
    "countryDescription": "",
    "countryFlag": "🇲🇨",
    "countryImage": null,
    "continent": "Europe"
  },
  {
    "name": "Montenegro",
    "capital": "Podgorica",
    "population": 620000,
    "independenceOrFormation": "2006",
    "formerColonialPower": "Serbia and Montenegro",
    "isd_code": "+382",
    "cctld": ".me",
    "countryDescription": "",
    "countryFlag": "🇲🇪",
    "countryImage": null,
    "continent": "Europe"
  },
  {
    "name": "Netherlands",
    "capital": "Amsterdam",
    "population": 18000000,
    "independenceOrFormation": "1581",
    "formerColonialPower": "Not colonized",
    "isd_code": "+31",
    "cctld": ".nl",
    "countryDescription": "",
    "countryFlag": "🇳🇱",
    "countryImage": null,
    "continent": "Europe"
  },
  {
    "name": "North Macedonia",
    "capital": "Skopje",
    "population": 2100000,
    "independenceOrFormation": "1991",
    "formerColonialPower": "Yugoslavia",
    "isd_code": "+389",
    "cctld": ".mk",
    "countryDescription": "",
    "countryFlag": "🇲🇰",
    "countryImage": null,
    "continent": "Europe"
  },
  {
    "name": "Norway",
    "capital": "Oslo",
    "population": 5600000,
    "independenceOrFormation": "1905",
    "formerColonialPower": "Sweden",
    "isd_code": "+47",
    "cctld": ".no",
    "countryDescription": "",
    "countryFlag": "🇳🇴",
    "countryImage": null,
    "continent": "Europe"
  },
  {
    "name": "Poland",
    "capital": "Warsaw",
    "population": 38000000,
    "independenceOrFormation": "1918",
    "formerColonialPower": "Partitioned",
    "isd_code": "+48",
    "cctld": ".pl",
    "countryDescription": "",
    "countryFlag": "🇵🇱",
    "countryImage": null,
    "continent": "Europe"
  },
  {
    "name": "Portugal",
    "capital": "Lisbon",
    "population": 10400000,
    "independenceOrFormation": "1143",
    "formerColonialPower": "Not colonized",
    "isd_code": "+351",
    "cctld": ".pt",
    "countryDescription": "",
    "countryFlag": "🇵🇹",
    "countryImage": null,
    "continent": "Europe"
  },
  {
    "name": "Romania",
    "capital": "Bucharest",
    "population": 19000000,
    "independenceOrFormation": "1877",
    "formerColonialPower": "Ottoman Empire",
    "isd_code": "+40",
    "cctld": ".ro",
    "countryDescription": "",
    "countryFlag": "🇷🇴",
    "countryImage": null,
    "continent": "Europe"
  },
  {
    "name": "Russia",
    "capital": "Moscow",
    "population": 146000000,
    "independenceOrFormation": "1991",
    "formerColonialPower": "Soviet Union",
    "isd_code": "+7",
    "cctld": ".ru",
    "countryDescription": "",
    "countryFlag": "🇷🇺",
    "countryImage": null,
    "continent": "Europe"
  },
  {
    "name": "San Marino",
    "capital": "San Marino",
    "population": 34000,
    "independenceOrFormation": "301",
    "formerColonialPower": "Not colonized",
    "isd_code": "+378",
    "cctld": ".sm",
    "countryDescription": "",
    "countryFlag": "🇸🇲",
    "countryImage": null,
    "continent": "Europe"
  },
  {
    "name": "Serbia",
    "capital": "Belgrade",
    "population": 6700000,
    "independenceOrFormation": "2006",
    "formerColonialPower": "Serbia and Montenegro",
    "isd_code": "+381",
    "cctld": ".rs",
    "countryDescription": "",
    "countryFlag": "🇷🇸",
    "countryImage": null,
    "continent": "Europe"
  },
  {
    "name": "Slovakia",
    "capital": "Bratislava",
    "population": 5400000,
    "independenceOrFormation": "1993",
    "formerColonialPower": "Czechoslovakia",
    "isd_code": "+421",
    "cctld": ".sk",
    "countryDescription": "",
    "countryFlag": "🇸🇰",
    "countryImage": null,
    "continent": "Europe"
  },
  {
    "name": "Slovenia",
    "capital": "Ljubljana",
    "population": 2100000,
    "independenceOrFormation": "1991",
    "formerColonialPower": "Yugoslavia",
    "isd_code": "+386",
    "cctld": ".si",
    "countryDescription": "",
    "countryFlag": "🇸🇮",
    "countryImage": null,
    "continent": "Europe"
  },
  {
    "name": "Spain",
    "capital": "Madrid",
    "population": 48000000,
    "independenceOrFormation": "1492",
    "formerColonialPower": "Not colonized",
    "isd_code": "+34",
    "cctld": ".es",
    "countryDescription": "",
    "countryFlag": "🇪🇸",
    "countryImage": null,
    "continent": "Europe"
  },
  {
    "name": "Sweden",
    "capital": "Stockholm",
    "population": 10600000,
    "independenceOrFormation": "1523",
    "formerColonialPower": "Not colonized",
    "isd_code": "+46",
    "cctld": ".se",
    "countryDescription": "",
    "countryFlag": "🇸🇪",
    "countryImage": null,
    "continent": "Europe"
  },
  {
    "name": "Switzerland",
    "capital": "Bern",
    "population": 8900000,
    "independenceOrFormation": "1291",
    "formerColonialPower": "Not colonized",
    "isd_code": "+41",
    "cctld": ".ch",
    "countryDescription": "",
    "countryFlag": "🇨🇭",
    "countryImage": null,
    "continent": "Europe"
  },
  {
    "name": "Ukraine",
    "capital": "Kyiv",
    "population": 38000000,
    "independenceOrFormation": "1991",
    "formerColonialPower": "Soviet Union",
    "isd_code": "+380",
    "cctld": ".ua",
    "countryDescription": "",
    "countryFlag": "🇺🇦",
    "countryImage": null,
    "continent": "Europe"
  },
  {
    "name": "United Kingdom",
    "capital": "London",
    "population": 68000000,
    "independenceOrFormation": "1707",
    "formerColonialPower": "Not colonized",
    "isd_code": "+44",
    "cctld": ".uk",
    "countryDescription": "",
    "countryFlag": "🇬🇧",
    "countryImage": null,
    "continent": "Europe"
  }
]
